teamgen/Match.py
teamgen/Meeting.py
teamgen/Team.py
teamgen/TeamGen.py
teamgen/__init__.py
teamgen/builder.py
teamgen/combo_builder.py
teamgen/exceptions.py
teamgen/history.py
teamgen/meeting_history.py
teamgen/meeting_utils.py
teamgen/player.py
teamgen/random_builder.py
teamgen/round.py
teamgen/stats.py
tennis-team-generator/Match.py
tennis-team-generator/Meeting.py
tennis-team-generator/Team.py
tennis-team-generator/TeamGen.py
tennis-team-generator/__init__.py
tennis-team-generator/builder.py
tennis-team-generator/combo_builder.py
tennis-team-generator/exceptions.py
tennis-team-generator/history.py
tennis-team-generator/meeting_history.py
tennis-team-generator/meeting_utils.py
tennis-team-generator/player.py
tennis-team-generator/random_builder.py
tennis-team-generator/round.py
tennis-team-generator/stats.py
tennis_team_generator/Match.py
tennis_team_generator/Meeting.py
tennis_team_generator/Team.py
tennis_team_generator/TeamGen.py
tennis_team_generator/__init__.py
tennis_team_generator/builder.py
tennis_team_generator/combo_builder.py
tennis_team_generator/exceptions.py
tennis_team_generator/history.py
tennis_team_generator/meeting_history.py
tennis_team_generator/meeting_utils.py
tennis_team_generator/player.py
tennis_team_generator/random_builder.py
tennis_team_generator/round.py
tennis_team_generator/stats.py
tests/__init__.py
tests/test_balanced_round.py
tests/test_history.py
tests/test_meeting.py
tests/test_meeting_stats.py
tests/test_round.py
tests/test_team.py
tests/test_unbalanced_round.py
teamgen-0.0.2.dist-info/LICENSE
teamgen-0.0.2.dist-info/METADATA
teamgen-0.0.2.dist-info/WHEEL
teamgen-0.0.2.dist-info/top_level.txt
teamgen-0.0.2.dist-info/RECORD
