Metadata-Version: 2.1
Name: teamgen
Version: 0.0.2
Summary: A basic, random team generator for tennis groups
Home-page: https://github.com/sharpertool/teamgen
Author: Ed Henderson
Author-email: ed@sharpertool.com
License: UNKNOWN
Platform: UNKNOWN
Classifier: Programming Language :: Python :: 3
Classifier: License :: OSI Approved :: MIT License
Classifier: Operating System :: OS Independent
Requires-Python: >=3.6
